.gitignore
LICENSE
MANIFEST.in
README.md
VERSION
requirements.txt
setup.py
uncertainty_framework/__init__.py
uncertainty_framework.egg-info/PKG-INFO
uncertainty_framework.egg-info/SOURCES.txt
uncertainty_framework.egg-info/dependency_links.txt
uncertainty_framework.egg-info/requires.txt
uncertainty_framework.egg-info/top_level.txt
uncertainty_framework/examples/__init__.py
uncertainty_framework/examples/sample.csv
uncertainty_framework/examples/variograms.py
uncertainty_framework/report/__init__.py
uncertainty_framework/report/_report.py
uncertainty_framework/report/console.py
uncertainty_framework/report/margins.py
uncertainty_framework/report/plot.py
uncertainty_framework/simulators/__init__.py
uncertainty_framework/simulators/_simulator.py
uncertainty_framework/simulators/monte_carlo.py