Metadata-Version: 2.1
Name: uncertainty-framework
Version: 0.2.0
Summary: Framework for propagating uncertainties through V-FOR-WaTer
Home-page: UNKNOWN
Author: Mirko Mälicke
Author-email: mirko.maelicke@kit.edu
License: MIT license
Platform: UNKNOWN
